{"directed": false, "graph": [["DateObtained", "21/10/10"], ["GeoLocation", "Canada, USA"], ["GeoExtent", "Country+"], ["DateModifier", "<"], ["Customer", 1], ["Network", "Bell Canada"], ["IX", 0], ["Provenance", "Secondary"], ["Note", "Corporate-only network. Check peering."], ["Source", "http://www.isp-planet.com/img/backbones/bell_canada.jpg"], ["Version", "1.0"], ["DateMonth", 0], ["DateYear", 0], ["Type", "COM"], ["LastAccess", "3/08/10"], ["Access", 1], ["Layer", "IP"], ["Creator", "Topology Zoo Toolset"], ["DateType", "Historic"], ["SourceGitVersion", "e278b1b"], ["Backbone", 1], ["Commercial", 0], ["NetworkDate", "<2005"], ["label", "Bellcanada"], ["LastProcessed", "2011_09_01"], ["Testbed", 0], ["Developed", 1], ["ToolsetVersion", "0.3.34dev-20120328"], ["Transit", 1]], "nodes": [{"Internal": 1, "Latitude": 54.45018, "Country": "Canada", "type": "City", "id": 0, "Longitude": -110.2017, "label": "Cold Lake"}, {"Internal": 1, "Latitude": 55.16667, "Country": "Canada", "type": "City", "id": 1, "Longitude": -118.80271, "label": "Grande Prairie"}, {"Internal": 1, "Latitude": 53.55014, "Country": "Canada", "type": "City", "id": 2, "Longitude": -113.46871, "label": "Edmonton"}, {"Internal": 1, "Latitude": 56.7335, "Country": "Canada", "type": "City", "id": 3, "Longitude": -111.38519, "label": "Fort McMurray"}, {"Internal": 1, "Latitude": 50.66648, "Country": "Canada", "type": "City", "id": 4, "Longitude": -120.3192, "label": "Kamloops"}, {"Internal": 1, "Latitude": 40.9126, "Country": "United States", "type": "City", "id": 5, "Longitude": -73.83708, "label": "Vernon"}, {"Internal": 1, "Latitude": 55.7666, "Country": "Canada", "type": "City", "id": 6, "Longitude": -120.23616, "label": "Dawson Creek"}, {"Internal": 1, "Latitude": 53.9166, "Country": "Canada", "type": "City", "id": 7, "Longitude": -122.75301, "label": "Prince George"}, {"Internal": 1, "Latitude": 49.88307, "Country": "Canada", "type": "City", "id": 8, "Longitude": -119.48568, "label": "Kelowna"}, {"Internal": 1, "Latitude": 49.48062, "Country": "Canada", "type": "City", "id": 9, "Longitude": -119.58584, "label": "Penticton?"}, {"Internal": 1, "Latitude": 50.20011, "Country": "Canada", "type": "City", "id": 10, "Longitude": -66.38208, "label": "Sept -Iles"}, {"Internal": 1, "Latitude": 46.23525, "Country": "Canada", "type": "City", "id": 11, "Longitude": -63.12671, "label": "Charlottetown"}, {"Internal": 1, "Latitude": 40.71427, "Country": "United States", "type": "City with Colocation", "id": 12, "Longitude": -74.00597, "label": "New York"}, {"Internal": 1, "Latitude": 45.41117, "Country": "Canada", "type": "City with Colocation", "id": 13, "Longitude": -75.69812, "label": "Ottawa"}, {"Internal": 1, "Latitude": 45.50884, "Country": "Canada", "type": "City", "id": 14, "Longitude": -73.58781, "label": "Montreal"}, {"Internal": 1, "Latitude": 45.40008, "Country": "Canada", "type": "City", "id": 15, "Longitude": -71.89908, "label": "Sherbrooke"}, {"Internal": 1, "Latitude": 46.81228, "Country": "Canada", "type": "City", "id": 16, "Longitude": -71.21454, "label": "Quebec City"}, {"Internal": 1, "Latitude": 48.42749, "Country": "Canada", "type": "City", "id": 17, "Longitude": -71.06352, "label": "Chicoutimi"}, {"Internal": 1, "Latitude": 48.44879, "Country": "Canada", "type": "City", "id": 18, "Longitude": -68.52396, "label": "Rimouski"}, {"Internal": 1, "Latitude": 49.21679, "Country": "Canada", "type": "City", "id": 19, "Longitude": -68.14894, "label": "Baie-Comeau"}, {"Internal": 1, "Latitude": 45.27271, "Country": "Canada", "type": "City", "id": 20, "Longitude": -66.06766, "label": "Saint John"}, {"Internal": 1, "Latitude": 46.11594, "Country": "Canada", "type": "City", "id": 21, "Longitude": -64.80186, "label": "Moncton"}, {"Internal": 1, "Latitude": 44.646, "Country": "Canada", "type": "City", "id": 22, "Longitude": -63.57333, "label": "Halifax"}, {"Internal": 1, "Latitude": 45.94541, "Country": "Canada", "type": "City", "id": 23, "Longitude": -66.66558, "label": "Fredericton"}, {"Internal": 1, "Latitude": 47.56494, "Country": "Canada", "type": "City", "id": 24, "Longitude": -52.70931, "label": "St John's"}, {"Internal": 1, "Latitude": 45.36685, "Country": "Canada", "type": "City", "id": 25, "Longitude": -63.28198, "label": "Onslow"}, {"Internal": 1, "Latitude": 49.69999, "Country": "Canada", "type": "City", "id": 26, "Longitude": -112.81856, "label": "Lethbridge"}, {"Internal": 1, "Latitude": 51.05011, "Country": "Canada", "type": "City with Colocation", "id": 27, "Longitude": -114.08529, "label": "Calgary"}, {"Internal": 1, "Latitude": 42.88645, "Country": "United States", "type": "City", "id": 28, "Longitude": -78.87837, "label": "Buffalo"}, {"Internal": 1, "Latitude": 43.70011, "Country": "Canada", "type": "City with Colocation", "id": 29, "Longitude": -79.4163, "label": "Toronto"}, {"Internal": 1, "Latitude": 48.43294, "Country": "Canada", "type": "City", "id": 30, "Longitude": -123.3693, "label": "Victoria"}, {"Internal": 1, "Latitude": 47.60621, "Country": "United States", "type": "City", "id": 31, "Longitude": -122.33207, "label": "Seattle"}, {"Internal": 1, "Latitude": 49.68657, "Country": "Canada", "type": "City", "id": 32, "Longitude": -124.9936, "label": "Courtenay"}, {"Internal": 1, "Latitude": 49.24966, "Country": "Canada", "type": "City with Colocation", "id": 33, "Longitude": -123.11934, "label": "Vancouver"}, {"Internal": 1, "Latitude": 41.85003, "Country": "United States", "type": "City", "id": 34, "Longitude": -87.65005, "label": "Chicago"}, {"Internal": 1, "Latitude": 34.05223, "Country": "United States", "type": "City", "id": 35, "Longitude": -118.24368, "label": "Los Angeles"}, {"Internal": 1, "Latitude": 37.44188, "Country": "United States", "type": "City", "id": 36, "Longitude": -122.14302, "label": "Palo Alto"}, {"Internal": 1, "Latitude": 37.77493, "Country": "United States", "type": "City", "id": 37, "Longitude": -122.41942, "label": "San Francisco"}, {"Internal": 1, "Latitude": 50.05006, "Country": "Canada", "type": "City", "id": 38, "Longitude": -110.66834, "label": "Medicine Hat"}, {"Internal": 1, "Latitude": 52.26682, "Country": "Canada", "type": "City", "id": 39, "Longitude": -113.802, "label": "Red Deer"}, {"Internal": 1, "Latitude": 38.89511, "Country": "United States", "type": "City", "id": 40, "Longitude": -77.03637, "label": "Washington"}, {"Internal": 1, "Latitude": 33.749, "Country": "United States", "type": "City", "id": 41, "Longitude": -84.38798, "label": "Atlanta"}, {"Internal": 1, "Latitude": 32.78306, "Country": "United States", "type": "City", "id": 42, "Longitude": -96.80667, "label": "Dallas"}, {"Internal": 1, "Latitude": 46.49, "Country": "Canada", "type": "City", "id": 43, "Longitude": -80.99001, "label": "Sudbury"}, {"Internal": 1, "Latitude": 48.4001, "Country": "Canada", "type": "City", "id": 44, "Longitude": -89.31683, "label": "Thunder Bay"}, {"Internal": 1, "Latitude": 49.8844, "Country": "Canada", "type": "City", "id": 45, "Longitude": -97.14704, "label": "Winnipeg"}, {"Internal": 1, "Latitude": 52.11679, "Country": "Canada", "type": "City", "id": 46, "Longitude": -106.63452, "label": "Saskatoon"}, {"Internal": 1, "Latitude": 50.45008, "Country": "Canada", "type": "City", "id": 47, "Longitude": -104.6178, "label": "Regina"}], "links": [{"LinkType": "Fiber", "source": 0, "LinkLabel": "Bell Canada Fiber Routes", "LinkNote": "Bell Canada  Routes", "target": 2}, {"LinkType": "Fiber", "source": 1, "LinkLabel": "Bell Canada Fiber Routes", "LinkNote": "Bell Canada  Routes", "target": 2}, {"LinkType": "Fiber", "source": 1, "LinkLabel": "Bell Canada Fiber Routes", "LinkNote": "Bell Canada  Routes", "target": 6}, {"LinkType": "Fiber", "source": 2, "LinkLabel": "Bell Canada Fiber Routes", "LinkNote": "Bell Canada  Routes", "target": 3}, {"LinkType": "Fiber", "source": 2, "LinkLabel": "Bell Canada Fiber Routes", "LinkNote": "Bell Canada  Routes", "target": 4}, {"LinkType": "Fiber", "source": 2, "LinkLabel": "Bell Canada Fiber Routes", "LinkNote": "Bell Canada  Routes", "target": 39}, {"LinkType": "Fiber", "source": 2, "LinkLabel": "Bell Canada Fiber Routes", "LinkNote": "Bell Canada  Routes", "target": 46}, {"LinkType": "Fiber", "source": 4, "LinkLabel": "Bell Canada Fiber Routes", "LinkNote": "Bell Canada  Routes", "target": 33}, {"LinkType": "Fiber", "source": 4, "LinkLabel": "Bell Canada Fiber Routes", "LinkNote": "Bell Canada  Routes", "target": 5}, {"LinkType": "Fiber", "source": 4, "LinkLabel": "Bell Canada Fiber Routes", "LinkNote": "Bell Canada  Routes", "target": 7}, {"LinkType": "Fiber", "source": 5, "LinkLabel": "Bell Canada Fiber Routes", "LinkNote": "Bell Canada  Routes", "target": 8}, {"LinkType": "Fiber", "source": 6, "LinkLabel": "Leased Fiber Route", "LinkNote": "Leased  Route", "target": 7}, {"LinkType": "Fiber", "source": 8, "LinkLabel": "Bell Canada Fiber Routes", "LinkNote": "Bell Canada  Routes", "target": 9}, {"LinkType": "Fiber", "source": 8, "LinkLabel": "Leased Fiber Route", "LinkNote": "Leased  Route", "target": 27}, {"LinkType": "Fiber", "source": 8, "LinkLabel": "Leased Fiber Route", "LinkNote": "Leased  Route", "target": 33}, {"LinkType": "Fiber", "source": 10, "LinkLabel": "Bell Canada Fiber Routes", "LinkNote": "Bell Canada  Routes", "target": 19}, {"LinkType": "Fiber", "source": 11, "LinkLabel": "Bell Canada Fiber Routes", "LinkNote": "Bell Canada  Routes", "target": 25}, {"LinkType": "Fiber", "source": 11, "LinkLabel": "Bell Canada Fiber Routes", "LinkNote": "Bell Canada  Routes", "target": 21}, {"LinkType": "Fiber", "source": 12, "LinkLabel": "Leased Fiber Route", "LinkNote": "Leased  Route", "target": 40}, {"LinkType": "Fiber", "source": 12, "LinkLabel": "Bell Canada Fiber Routes", "LinkNote": "Bell Canada  Routes", "target": 28}, {"LinkType": "Fiber", "source": 12, "LinkLabel": "Bell Canada Fiber Routes", "LinkNote": "Bell Canada  Routes", "target": 14}, {"LinkType": "Fiber", "source": 13, "LinkLabel": "Bell Canada Fiber Routes", "LinkNote": "Bell Canada  Routes", "target": 29}, {"LinkType": "Fiber", "source": 13, "LinkLabel": "Bell Canada Fiber Routes", "LinkNote": "Bell Canada  Routes", "target": 14}, {"LinkType": "Fiber", "source": 14, "LinkLabel": "Bell Canada Fiber Routes", "LinkNote": "Bell Canada  Routes", "target": 16}, {"LinkType": "Fiber", "source": 14, "LinkLabel": "Bell Canada Fiber Routes", "LinkNote": "Bell Canada  Routes", "target": 15}, {"LinkType": "Fiber", "source": 15, "LinkLabel": "Bell Canada Fiber Routes", "LinkNote": "Bell Canada  Routes", "target": 16}, {"LinkType": "Fiber", "source": 15, "LinkLabel": "Bell Canada Fiber Routes", "LinkNote": "Bell Canada  Routes", "target": 16}, {"LinkType": "Fiber", "source": 16, "LinkLabel": "Bell Canada Fiber Routes", "LinkNote": "Bell Canada  Routes", "target": 17}, {"LinkType": "Fiber", "source": 16, "LinkLabel": "Bell Canada Fiber Routes", "LinkNote": "Bell Canada  Routes", "target": 23}, {"LinkType": "Fiber", "source": 16, "LinkLabel": "Bell Canada Fiber Routes", "LinkNote": "Bell Canada  Routes", "target": 21}, {"LinkType": "Fiber", "source": 17, "LinkLabel": "Bell Canada Fiber Routes", "LinkNote": "Bell Canada  Routes", "target": 18}, {"LinkType": "Fiber", "source": 18, "LinkLabel": "Bell Canada Fiber Routes", "LinkNote": "Bell Canada  Routes", "target": 19}, {"LinkType": "Fiber", "source": 20, "LinkLabel": "Bell Canada Fiber Routes", "LinkNote": "Bell Canada  Routes", "target": 21}, {"LinkType": "Fiber", "source": 20, "LinkLabel": "Bell Canada Fiber Routes", "LinkNote": "Bell Canada  Routes", "target": 22}, {"LinkType": "Fiber", "source": 20, "LinkLabel": "Bell Canada Fiber Routes", "LinkNote": "Bell Canada  Routes", "target": 23}, {"LinkType": "Fiber", "source": 21, "LinkLabel": "Bell Canada Fiber Routes", "LinkNote": "Bell Canada  Routes", "target": 25}, {"LinkType": "Fiber", "source": 22, "LinkLabel": "Bell Canada Fiber Routes", "LinkNote": "Bell Canada  Routes", "target": 24}, {"LinkType": "Fiber", "source": 22, "LinkLabel": "Bell Canada Fiber Routes", "LinkNote": "Bell Canada  Routes", "target": 25}, {"LinkType": "Fiber", "source": 24, "LinkLabel": "Bell Canada Fiber Routes", "LinkNote": "Bell Canada  Routes", "target": 25}, {"LinkType": "Fiber", "source": 26, "LinkLabel": "Bell Canada Fiber Routes", "LinkNote": "Bell Canada  Routes", "target": 27}, {"LinkType": "Fiber", "source": 27, "LinkLabel": "Bell Canada Fiber Routes", "LinkNote": "Bell Canada  Routes", "target": 33}, {"LinkType": "Fiber", "source": 27, "LinkLabel": "Bell Canada Fiber Routes", "LinkNote": "Bell Canada  Routes", "target": 38}, {"LinkType": "Fiber", "source": 27, "LinkLabel": "Bell Canada Fiber Routes", "LinkNote": "Bell Canada  Routes", "target": 39}, {"LinkType": "Fiber", "source": 28, "LinkLabel": "Bell Canada Fiber Routes", "LinkNote": "Bell Canada  Routes", "target": 29}, {"LinkType": "Fiber", "source": 29, "LinkLabel": "Bell Canada Fiber Routes", "LinkNote": "Bell Canada  Routes", "target": 34}, {"LinkType": "Fiber", "source": 29, "LinkLabel": "Bell Canada Fiber Routes", "LinkNote": "Bell Canada  Routes", "target": 43}, {"LinkType": "Fiber", "source": 30, "LinkLabel": "Bell Canada Fiber Routes", "LinkNote": "Bell Canada  Routes", "target": 32}, {"LinkType": "Fiber", "source": 30, "LinkLabel": "Bell Canada Fiber Routes", "LinkNote": "Bell Canada  Routes", "target": 33}, {"LinkType": "Fiber", "source": 30, "LinkLabel": "Bell Canada Fiber Routes", "LinkNote": "Bell Canada  Routes", "target": 31}, {"LinkType": "Fiber", "source": 31, "LinkLabel": "Bell Canada Fiber Routes", "LinkNote": "Bell Canada  Routes", "target": 33}, {"LinkType": "Fiber", "source": 31, "LinkLabel": "Leased Fiber Route", "LinkNote": "Leased  Route", "target": 35}, {"LinkType": "Fiber", "source": 31, "LinkLabel": "Leased Fiber Route", "LinkNote": "Leased  Route", "target": 36}, {"LinkType": "Fiber", "source": 31, "LinkLabel": "Leased Fiber Route", "LinkNote": "Leased  Route", "target": 37}, {"LinkType": "Fiber", "source": 34, "LinkLabel": "Leased Fiber Route", "LinkNote": "Leased  Route", "target": 42}, {"LinkType": "Fiber", "source": 34, "LinkLabel": "Bell Canada Fiber Routes", "LinkNote": "Bell Canada  Routes", "target": 45}, {"LinkType": "Fiber", "source": 35, "LinkLabel": "Leased Fiber Route", "LinkNote": "Leased  Route", "target": 40}, {"LinkType": "Fiber", "source": 35, "LinkLabel": "Leased Fiber Route", "LinkNote": "Leased  Route", "target": 36}, {"LinkType": "Fiber", "source": 36, "LinkLabel": "Leased Fiber Route", "LinkNote": "Leased  Route", "target": 37}, {"LinkType": "Fiber", "source": 38, "LinkLabel": "Bell Canada Fiber Routes", "LinkNote": "Bell Canada  Routes", "target": 47}, {"LinkType": "Fiber", "source": 40, "LinkLabel": "Leased Fiber Route", "LinkNote": "Leased  Route", "target": 41}, {"LinkType": "Fiber", "source": 41, "LinkLabel": "Leased Fiber Route", "LinkNote": "Leased  Route", "target": 42}, {"LinkType": "Fiber", "source": 43, "LinkLabel": "Bell Canada Fiber Routes", "LinkNote": "Bell Canada  Routes", "target": 44}, {"LinkType": "Fiber", "source": 44, "LinkLabel": "Bell Canada Fiber Routes", "LinkNote": "Bell Canada  Routes", "target": 45}, {"LinkType": "Fiber", "source": 45, "LinkLabel": "Bell Canada Fiber Routes", "LinkNote": "Bell Canada  Routes", "target": 46}, {"LinkType": "Fiber", "source": 45, "LinkLabel": "Bell Canada Fiber Routes", "LinkNote": "Bell Canada  Routes", "target": 47}], "multigraph": true}