{"directed": false, "graph": [["DateObtained", "16/01/11"], ["GeoLocation", "Europe"], ["GeoExtent", "Continent"], ["DateModifier", "="], ["Customer", 1], ["Network", "BICS"], ["IX", 0], ["Provenance", "Primary"], ["Note", "Can't nail down transit"], ["Source", "http://bics.com/index.php/network/european-network/"], ["Version", "1.0"], ["DateMonth", "01"], ["DateYear", "2011"], ["DateType", "Current"], ["LastAccess", "16/01/11"], ["Access", 0], ["Layer", "IP"], ["Creator", "Topology Zoo Toolset"], ["Type", "COM"], ["SourceGitVersion", "e278b1b"], ["Backbone", 1], ["Commercial", 0], ["NetworkDate", "2011_01"], ["label", "Bics"], ["LastProcessed", "2011_09_01"], ["Testbed", 0], ["Developed", 1], ["ToolsetVersion", "0.3.34dev-20120328"], ["Transit", 0]], "nodes": [{"Internal": 1, "Latitude": 48.14816, "Country": "Slovakia", "type": "PoP", "id": 0, "Longitude": 17.10674, "label": "Bratislava"}, {"Internal": 1, "Latitude": 48.20849, "Country": "Austria", "type": "PoP", "id": 1, "Longitude": 16.37208, "label": "Vienna"}, {"Internal": 1, "Latitude": 50.08804, "Country": "Czech Republic", "type": "PoP", "id": 2, "Longitude": 14.42076, "label": "Praha"}, {"Internal": 1, "Latitude": 51.9225, "Country": "Netherlands", "type": "PoP", "id": 3, "Longitude": 4.47917, "label": "Rotterdam"}, {"Internal": 1, "Latitude": 41.89474, "Country": "Italy", "type": "PoP", "id": 4, "Longitude": 12.4839, "label": "Roma"}, {"Internal": 1, "Latitude": 47.49801, "Country": "Hungary", "type": "PoP", "id": 5, "Longitude": 19.03991, "label": "Budapest"}, {"Internal": 1, "Latitude": 46.05108, "Country": "Slovenia", "type": "PoP", "id": 6, "Longitude": 14.50513, "label": "Ljubjana"}, {"Internal": 1, "Latitude": 45.81444, "Country": "Croatia", "type": "PoP", "id": 7, "Longitude": 15.97798, "label": "Zagreb"}, {"Internal": 1, "Latitude": 44.43225, "Country": "Romania", "type": "PoP", "id": 8, "Longitude": 26.10626, "label": "Bucharest"}, {"Internal": 1, "Latitude": 41.01384, "Country": "Turkey", "type": "PoP", "id": 9, "Longitude": 28.94966, "label": "Istanbul"}, {"Internal": 1, "Latitude": 47.14151, "Country": "Liechtenstein", "type": "PoP", "id": 10, "Longitude": 9.52154, "label": "Vaduz"}, {"Internal": 1, "Latitude": 48.58333, "Country": "France", "type": "PoP", "id": 11, "Longitude": 7.75, "label": "Strasbourg"}, {"Internal": 1, "Latitude": 49.61167, "Country": "Luxembourg", "type": "PoP", "id": 12, "Longitude": 6.13, "label": "Luxembourg"}, {"Internal": 1, "Latitude": 47.36667, "Country": "Switzerland", "type": "Cityring", "id": 13, "Longitude": 8.55, "label": "Zurich"}, {"Internal": 1, "Latitude": 50.85045, "Country": "Belgium", "type": "Cityring", "id": 14, "Longitude": 4.34878, "label": "Brussels"}, {"Internal": 1, "Latitude": 46.20222, "Country": "Switzerland", "type": "Cityring", "id": 15, "Longitude": 6.14569, "label": "Geneva"}, {"Internal": 1, "Latitude": 45.46427, "Country": "Italy", "type": "Cityring", "id": 16, "Longitude": 9.18951, "label": "Milan"}, {"Internal": 1, "Latitude": 37.97945, "Country": "Greece", "type": "PoP", "id": 17, "Longitude": 23.71622, "label": "Athens"}, {"Internal": 1, "Latitude": 42.69751, "Country": "Bulgaria", "type": "PoP", "id": 18, "Longitude": 23.32415, "label": "Sofia"}, {"Internal": 1, "Latitude": 50.11667, "Country": "Germany", "type": "Cityring", "id": 19, "Longitude": 8.68333, "label": "Frankfurt"}, {"Internal": 1, "Latitude": 52.37403, "Country": "Netherlands", "type": "Cityring", "id": 20, "Longitude": 4.88969, "label": "Amsterdam"}, {"Internal": 1, "Latitude": 51.50853, "Country": "United Kingdom", "type": "Cityring", "id": 21, "Longitude": -0.12574, "label": "London"}, {"Internal": 1, "Latitude": 48.85341, "Country": "France", "type": "Cityring", "id": 22, "Longitude": 2.3488, "label": "Paris"}, {"Internal": 1, "Latitude": 59.33258, "Country": "Sweden", "type": "PoP", "id": 23, "Longitude": 18.0649, "label": "Stockholm"}, {"Internal": 1, "Latitude": 52.22977, "Country": "Poland", "type": "PoP", "id": 24, "Longitude": 21.01178, "label": "Warsaw"}, {"Internal": 1, "Latitude": 50.45466, "Country": "Ukraine", "type": "PoP", "id": 25, "Longitude": 30.5238, "label": "Kiev"}, {"Internal": 1, "Latitude": 53.34399, "Country": "Ireland", "type": "PoP", "id": 26, "Longitude": -6.26719, "label": "Dublin"}, {"Internal": 1, "Latitude": 38.71667, "Country": "Portugal", "type": "PoP", "id": 27, "Longitude": -9.13333, "label": "Lisbon"}, {"Internal": 1, "Latitude": 40.4165, "Country": "Spain", "type": "PoP", "id": 28, "Longitude": -3.70256, "label": "Madrid"}, {"Internal": 1, "Latitude": 41.38879, "Country": "Spain", "type": "PoP", "id": 29, "Longitude": 2.15899, "label": "Barcelona"}, {"Internal": 1, "Latitude": 43.29695, "Country": "France", "type": "PoP", "id": 30, "Longitude": 5.38107, "label": "Marseille"}, {"Internal": 1, "Latitude": 45.75, "Country": "France", "type": "PoP", "id": 31, "Longitude": 4.85, "label": "Lyon"}, {"Internal": 1, "Latitude": 47.56667, "Country": "Switzerland", "type": "PoP", "id": 32, "Longitude": 7.6, "label": "Basel"}], "links": [{"LinkType": "SDH", "source": 0, "LinkLabel": "SDH", "target": 1}, {"LinkType": "SDH", "source": 0, "LinkLabel": "SDH", "target": 2}, {"LinkType": "SDH", "source": 0, "LinkLabel": "SDH", "target": 5}, {"LinkType": "SDH", "source": 1, "LinkLabel": "SDH", "target": 16}, {"LinkType": "SDH", "source": 1, "LinkLabel": "SDH", "target": 19}, {"LinkType": "SDH", "source": 2, "LinkLabel": "SDH", "target": 24}, {"LinkType": "SDH", "source": 2, "LinkLabel": "SDH", "target": 19}, {"LinkType": "Fiber", "source": 3, "LinkLabel": "Optic Fiber", "LinkNote": "Optic ", "target": 20}, {"LinkType": "Fiber", "source": 3, "LinkLabel": "Optic Fiber", "LinkNote": "Optic ", "target": 14}, {"LinkType": "SDH", "source": 4, "LinkLabel": "SDH", "target": 16}, {"LinkType": "SDH", "source": 4, "LinkLabel": "SDH", "target": 13}, {"LinkType": "SDH", "source": 5, "LinkLabel": "SDH", "target": 8}, {"LinkType": "SDH", "source": 5, "LinkLabel": "SDH", "target": 18}, {"LinkType": "SDH", "source": 5, "LinkLabel": "SDH", "target": 7}, {"LinkType": "SDH", "source": 6, "LinkLabel": "SDH", "target": 7}, {"LinkType": "SDH", "source": 8, "LinkLabel": "SDH", "target": 25}, {"LinkType": "SDH", "source": 8, "LinkLabel": "SDH", "target": 9}, {"LinkType": "SDH", "source": 9, "LinkLabel": "SDH", "target": 17}, {"LinkType": "SDH", "source": 10, "LinkLabel": "SDH", "target": 13}, {"LinkType": "SDH", "source": 11, "LinkLabel": "SDH", "target": 32}, {"LinkType": "Fiber", "source": 11, "LinkLabel": "Optic Fiber", "LinkNote": "Optic ", "target": 19}, {"LinkType": "SDH", "source": 11, "LinkLabel": "SDH", "target": 12}, {"LinkType": "Fiber", "source": 12, "LinkLabel": "Optic Fiber", "LinkNote": "Optic ", "target": 14}, {"LinkType": "Fiber", "source": 13, "LinkLabel": "Optic Fiber", "LinkNote": "Optic ", "target": 16}, {"LinkType": "Fiber", "source": 13, "LinkLabel": "Optic Fiber", "LinkNote": "Optic ", "target": 19}, {"LinkType": "Fiber", "source": 13, "LinkLabel": "Optic Fiber", "LinkNote": "Optic ", "target": 15}, {"LinkType": "Fiber", "source": 14, "LinkLabel": "Optic Fiber", "LinkNote": "Optic ", "target": 19}, {"LinkType": "Fiber", "source": 14, "LinkLabel": "Optic Fiber", "LinkNote": "Optic ", "target": 20}, {"LinkType": "Fiber", "source": 14, "LinkLabel": "Optic Fiber", "LinkNote": "Optic ", "target": 21}, {"LinkType": "Fiber", "source": 14, "LinkLabel": "Optic Fiber", "LinkNote": "Optic ", "target": 22}, {"LinkType": "Fiber", "source": 15, "LinkLabel": "Optic Fiber", "LinkNote": "Optic ", "target": 32}, {"LinkType": "Fiber", "source": 15, "LinkLabel": "Optic Fiber", "LinkNote": "Optic ", "target": 22}, {"LinkType": "Fiber", "source": 15, "LinkLabel": "Optic Fiber", "LinkNote": "Optic ", "target": 31}, {"LinkType": "Fiber", "source": 16, "LinkLabel": "Optic Fiber", "LinkNote": "Optic ", "target": 30}, {"LinkType": "SDH", "source": 17, "LinkLabel": "SDH", "target": 18}, {"LinkType": "Fiber", "source": 19, "LinkLabel": "Optic Fiber", "LinkNote": "Optic ", "target": 20}, {"LinkType": "SDH", "source": 19, "LinkLabel": "SDH", "target": 23}, {"LinkType": "SDH", "source": 19, "LinkLabel": "SDH", "target": 24}, {"LinkType": "Fiber", "source": 20, "LinkLabel": "Optic Fiber", "LinkNote": "Optic ", "target": 21}, {"LinkType": "SDH", "source": 21, "LinkLabel": "SDH", "target": 26}, {"LinkType": "SDH", "source": 21, "LinkLabel": "SDH", "target": 27}, {"LinkType": "Fiber", "source": 21, "LinkLabel": "Optic Fiber", "LinkNote": "Optic ", "target": 22}, {"LinkType": "Fiber", "source": 22, "LinkLabel": "Optic Fiber", "LinkNote": "Optic ", "target": 31}, {"LinkType": "SDH", "source": 22, "LinkLabel": "SDH", "target": 28}, {"LinkType": "SDH", "source": 24, "LinkLabel": "SDH", "target": 25}, {"LinkType": "SDH", "source": 28, "LinkLabel": "SDH", "target": 29}, {"LinkType": "SDH", "source": 29, "LinkLabel": "SDH", "target": 30}, {"LinkType": "Fiber", "source": 30, "LinkLabel": "Optic Fiber", "LinkNote": "Optic ", "target": 31}], "multigraph": true}