{"directed": false, "graph": [["DateObtained", "22/10/10"], ["GeoLocation", "Japan"], ["GeoExtent", "Country"], ["DateModifier", "="], ["Customer", 0], ["Network", "Sinet"], ["IX", 0], ["Provenance", "Primary"], ["Access", 0], ["Source", "http://www.sinet.ad.jp/topology"], ["Version", "1.0"], ["DateMonth", "08"], ["DateYear", "2010"], ["DateType", "Current"], ["LastAccess", "3/08/10"], ["Layer", "IP"], ["Creator", "Topology Zoo Toolset"], ["Type", "REN"], ["SourceGitVersion", "e278b1b"], ["Backbone", 1], ["Commercial", 0], ["NetworkDate", "2010_08"], ["label", "Sinet"], ["LastProcessed", "2011_09_01"], ["Testbed", 0], ["Developed", 1], ["ToolsetVersion", "0.3.34dev-20120328"], ["Transit", 0]], "nodes": [{"Internal": 1, "Latitude": 33.60639, "Country": "Japan", "type": "Core Node", "id": 0, "Longitude": 130.41806, "label": "Fukuoka DC"}, {"Internal": 1, "Latitude": 33.23806, "Country": "Japan", "type": "Edge Node", "id": 1, "Longitude": 131.6125, "label": "Oita U"}, {"Internal": 1, "Latitude": 33.0, "Country": "Japan", "type": "Edge Node", "id": 2, "Longitude": 131.0, "label": "Kyushu U"}, {"Internal": 1, "type": "Edge Node", "id": 3, "label": "Kyushu IT"}, {"Internal": 1, "Latitude": 34.39627, "Country": "Japan", "type": "Edge Node", "id": 4, "Longitude": 132.45937, "label": "Hiroshima U"}, {"Internal": 1, "Latitude": 34.39627, "Country": "Japan", "type": "Core Node", "id": 5, "Longitude": 132.45937, "label": "Hiroshima DC"}, {"Internal": 1, "Latitude": 33.83916, "Country": "Japan", "type": "Edge Node", "id": 6, "Longitude": 132.76574, "label": "Ehime U"}, {"Internal": 1, "Latitude": 34.18583, "Country": "Japan", "type": "Edge Node", "id": 7, "Longitude": 131.47139, "label": "Yamaguchi U"}, {"Internal": 1, "type": "Edge Node", "id": 8, "label": "IMS, U Tokyo"}, {"Internal": 1, "type": "Edge Node", "id": 9, "label": "ISSP, U Tokyo"}, {"Internal": 1, "Latitude": 33.83916, "Country": "Japan", "type": "Core Node", "id": 10, "Longitude": 132.76574, "label": "Matsuyama DC"}, {"Internal": 1, "Latitude": 34.34028, "Country": "Japan", "type": "Edge Node", "id": 11, "Longitude": 134.04333, "label": "Kagawa U"}, {"Internal": 1, "type": "Edge Node", "id": 12, "label": "Kamioka Obs, ICRR, U Tokyo"}, {"Internal": 1, "Latitude": 35.60472, "Country": "Japan", "type": "Edge Node", "id": 13, "Longitude": 140.12333, "label": "Chiba U"}, {"Internal": 1, "Latitude": 35.16667, "Country": "Japan", "type": "Edge Node", "id": 14, "Longitude": 133.56667, "label": "Shinshu U"}, {"Internal": 1, "type": "Edge Node", "id": 15, "label": "NIFS"}, {"Internal": 1, "Latitude": 36.59444, "Country": "Japan", "type": "Edge Node", "id": 16, "Longitude": 136.62556, "label": "Kanazawa U"}, {"Internal": 1, "type": "Edge Node", "id": 17, "label": "JAIST"}, {"Internal": 1, "Latitude": 34.80559, "Country": "Japan", "type": "Edge Node", "id": 18, "Longitude": 135.77841, "label": "Doshisha U"}, {"Internal": 1, "type": "Edge Node", "id": 19, "label": "ICR, Kyoto U"}, {"Internal": 1, "Latitude": 35.18147, "Country": "Japan", "type": "Core Node", "id": 20, "Longitude": 136.90641, "label": "Nagoya DC"}, {"Internal": 1, "type": "Edge Node", "id": 21, "label": "NINS-Okazaki"}, {"Internal": 1, "Latitude": 34.97694, "Country": "Japan", "type": "Edge Node", "id": 22, "Longitude": 138.38306, "label": "Shizuoka U"}, {"Internal": 1, "Latitude": 35.18147, "Country": "Japan", "type": "Edge Node", "id": 23, "Longitude": 136.90641, "label": "Nagoya U"}, {"Internal": 1, "Latitude": 36.59444, "Country": "Japan", "type": "Core Node", "id": 24, "Longitude": 136.62556, "label": "Kanazawa DC"}, {"Internal": 1, "Latitude": 36.69528, "Country": "Japan", "type": "Edge Node", "id": 25, "Longitude": 137.21139, "label": "Toyama U"}, {"Internal": 1, "Latitude": 35.66389, "Country": "Japan", "type": "Edge Node", "id": 26, "Longitude": 138.56833, "label": "Yamanashi U"}, {"Internal": 1, "Latitude": 34.06583, "Country": "Japan", "type": "Edge Node", "id": 27, "Longitude": 134.55944, "label": "U Tokushima"}, {"Internal": 1, "Latitude": 35.61488, "Country": "Japan", "type": "Core Node", "id": 28, "Longitude": 139.5813, "label": "Tokyo DC3"}, {"Internal": 1, "type": "Edge Node", "id": 29, "label": "NII"}, {"Internal": 1, "type": "Edge Node", "id": 30, "label": "NII-CHiba"}, {"Internal": 1, "type": "Edge Node", "id": 31, "label": "GSIST, U Tokyo"}, {"Internal": 1, "type": "Edge Node", "id": 32, "label": "U Electro-Communications"}, {"Internal": 1, "type": "Edge Node", "id": 33, "label": "RIKEN"}, {"Internal": 1, "Latitude": 35.61488, "Country": "Japan", "type": "Core Node", "id": 34, "Longitude": 139.5813, "label": "Tokyo DC1"}, {"Internal": 1, "Latitude": 35.61488, "Country": "Japan", "type": "Core Node", "id": 35, "Longitude": 139.5813, "label": "Tokyo DC2"}, {"Internal": 1, "type": "Edge Node", "id": 36, "label": "JAXA-ISAS"}, {"Internal": 1, "type": "Edge Node", "id": 37, "label": "Yokohama National U"}, {"Internal": 1, "Latitude": 35.62522, "Country": "Japan", "type": "Edge Node", "id": 38, "Longitude": 139.42416, "label": "Keio U"}, {"Internal": 1, "type": "Edge Node", "id": 39, "label": "Tokyo IT"}, {"Internal": 1, "Latitude": 37.90222, "Country": "Japan", "type": "Edge Node", "id": 40, "Longitude": 139.02361, "label": "Niigata U"}, {"Internal": 1, "Latitude": 36.06443, "Country": "Japan", "type": "Edge Node", "id": 41, "Longitude": 136.22257, "label": "Fukui U"}, {"Internal": 1, "type": "Edge Node", "id": 42, "label": "KEK"}, {"Internal": 1, "type": "Edge Node", "id": 43, "label": "JAEA"}, {"Internal": 1, "Latitude": 36.2, "Country": "Japan", "type": "Core Node", "id": 44, "Longitude": 140.1, "label": "Tsukuba DC"}, {"Internal": 1, "Latitude": 36.2, "Country": "Japan", "type": "Edge Node", "id": 45, "Longitude": 140.1, "label": "U Tsukuba"}, {"Internal": 1, "Latitude": 36.39111, "Country": "Japan", "type": "Edge Node", "id": 46, "Longitude": 139.06083, "label": "Gunma U"}, {"Internal": 1, "type": "Edge Node", "id": 47, "label": "ISM"}, {"Internal": 1, "Latitude": 35.61488, "Country": "Japan", "type": "Edge Node", "id": 48, "Longitude": 139.5813, "label": "U Tokyo"}, {"Internal": 1, "Latitude": 35.02107, "Country": "Japan", "type": "Core Node", "id": 49, "Longitude": 135.75385, "label": "Kyoto DC"}, {"Internal": 1, "Latitude": 35.02107, "Country": "Japan", "type": "Edge Node", "id": 50, "Longitude": 135.75385, "label": "Kyoto U"}, {"Internal": 1, "Latitude": 38.3, "Country": "Japan", "type": "Edge Node", "id": 51, "Longitude": 139.55, "label": "Waseda U"}, {"Internal": 1, "Latitude": 34.27339, "Country": "Japan", "type": "Edge Node", "id": 52, "Longitude": 136.5065, "label": "Kansai U"}, {"Internal": 1, "Latitude": 34.69374, "Country": "Japan", "type": "Edge Node", "id": 53, "Longitude": 135.50218, "label": "Osaka U"}, {"Internal": 1, "Latitude": 34.6913, "Country": "Japan", "type": "Edge Node", "id": 54, "Longitude": 135.183, "label": "Kobe U"}, {"Internal": 1, "type": "Edge Node", "id": 55, "label": "JAMSTEC"}, {"Internal": 1, "type": "Edge Node", "id": 56, "label": "JASRI"}, {"Internal": 1, "Latitude": 35.5, "Country": "Japan", "type": "Edge Node", "id": 57, "Longitude": 134.23333, "label": "Tottori U"}, {"Internal": 1, "Latitude": 34.66167, "Country": "Japan", "type": "Edge Node", "id": 58, "Longitude": 133.935, "label": "Okayama U"}, {"Internal": 1, "Latitude": 34.69374, "Country": "Japan", "type": "Core Node", "id": 59, "Longitude": 135.50218, "label": "Osaka DC"}, {"Internal": 1, "type": "Edge Node", "id": 60, "label": "NAOJ"}, {"Internal": 1, "Latitude": 35.90807, "Country": "Japan", "type": "Edge Node", "id": 61, "Longitude": 139.65657, "label": "Saitama U"}, {"Internal": 1, "type": "Edge Node", "id": 62, "label": "JAXA-IAT"}, {"Internal": 1, "type": "Edge Node", "id": 63, "label": "Tokyo U Ag and Tech"}, {"Internal": 1, "Latitude": 32.74472, "Country": "Japan", "type": "Edge Node", "id": 64, "Longitude": 129.87361, "label": "Nagasaki U"}, {"Internal": 1, "type": "Edge Node", "id": 65, "label": "Kurnamoto U"}, {"Internal": 1, "Latitude": 43.06417, "Country": "Japan", "type": "Core Node", "id": 66, "Longitude": 141.34694, "label": "Sapporo DC"}, {"Internal": 1, "Latitude": 43.06417, "Country": "Japan", "type": "Edge Node", "id": 67, "Longitude": 141.34694, "label": "Hokkaido U"}, {"Internal": 1, "type": "Edge Node", "id": 68, "label": "Kitami IT"}, {"Internal": 1, "Latitude": 40.59306, "Country": "Japan", "type": "Edge Node", "id": 69, "Longitude": 140.4725, "label": "Hirosaki U"}, {"Internal": 1, "Latitude": 38.26889, "Country": "Japan", "type": "Core Node", "id": 70, "Longitude": 140.87194, "label": "Sendai DC"}, {"Internal": 1, "Latitude": 32.76667, "Country": "Japan", "type": "Edge Node", "id": 71, "Longitude": 131.36667, "label": "Tohoku U"}, {"Internal": 1, "type": "Edge Node", "id": 72, "label": "U of the Ryukyus"}, {"Internal": 1, "Latitude": 31.56018, "Country": "Japan", "type": "Edge Node", "id": 73, "Longitude": 130.55814, "label": "Kagoshima U"}], "links": [{"source": 0, "LinkLabel": "1-20Gbps", "target": 64}, {"source": 0, "LinkLabel": "1-20Gbps", "target": 1}, {"source": 0, "LinkLabel": "1-20Gbps", "target": 2}, {"source": 0, "LinkLabel": "1-20Gbps", "target": 3}, {"source": 0, "LinkLabel": "10-20Gbps", "target": 5}, {"source": 0, "LinkLabel": "1-20Gbps", "target": 65}, {"source": 0, "LinkLabel": "1-20Gbps", "target": 72}, {"source": 0, "LinkLabel": "1-20Gbps", "target": 73}, {"source": 0, "LinkLabel": "10-20Gbps", "target": 10}, {"source": 4, "LinkLabel": "1-20Gbps", "target": 5}, {"source": 5, "LinkLabel": "1-20Gbps", "target": 7}, {"source": 5, "LinkLabel": "10-20Gbps", "target": 49}, {"source": 5, "LinkLabel": "1-20Gbps", "target": 57}, {"source": 5, "LinkLabel": "1-20Gbps", "target": 58}, {"source": 6, "LinkLabel": "1-20Gbps", "target": 10}, {"source": 8, "LinkLabel": "1-20Gbps", "target": 34}, {"source": 9, "LinkLabel": "1-20Gbps", "target": 34}, {"source": 10, "LinkLabel": "1-20Gbps", "target": 11}, {"source": 10, "LinkLabel": "1-20Gbps", "target": 27}, {"source": 10, "LinkLabel": "10-20Gbps", "target": 59}, {"source": 12, "LinkLabel": "1-20Gbps", "target": 20}, {"source": 13, "LinkLabel": "1-20Gbps", "target": 35}, {"source": 14, "LinkLabel": "1-20Gbps", "target": 35}, {"source": 15, "LinkLabel": "1-20Gbps", "target": 20}, {"source": 16, "LinkLabel": "1-20Gbps", "target": 24}, {"source": 17, "LinkLabel": "1-20Gbps", "target": 24}, {"source": 18, "LinkLabel": "1-20Gbps", "target": 49}, {"source": 19, "LinkLabel": "1-20Gbps", "target": 49}, {"LinkSpeed": "40", "source": 20, "LinkLabel": "40Gbps", "target": 34, "LinkSpeedUnits": "G", "LinkSpeedRaw": 40000000000.0}, {"source": 20, "LinkLabel": "1-20Gbps", "target": 21}, {"source": 20, "LinkLabel": "1-20Gbps", "target": 22}, {"source": 20, "LinkLabel": "1-20Gbps", "target": 23}, {"LinkSpeed": "40", "source": 20, "LinkLabel": "40Gbps", "target": 59, "LinkSpeedUnits": "G", "LinkSpeedRaw": 40000000000.0}, {"source": 24, "LinkLabel": "10-20Gbps", "target": 66}, {"source": 24, "LinkLabel": "10-20Gbps", "target": 35}, {"source": 24, "LinkLabel": "10-20Gbps", "target": 49}, {"source": 24, "LinkLabel": "1-20Gbps", "target": 40}, {"source": 24, "LinkLabel": "1-20Gbps", "target": 41}, {"source": 24, "LinkLabel": "1-20Gbps", "target": 25}, {"source": 26, "LinkLabel": "1-20Gbps", "target": 35}, {"source": 28, "LinkLabel": "1-20Gbps", "target": 35}, {"source": 29, "LinkLabel": "1-20Gbps", "target": 34}, {"source": 30, "LinkLabel": "1-20Gbps", "target": 34}, {"source": 31, "LinkLabel": "1-20Gbps", "target": 34}, {"source": 32, "LinkLabel": "1-20Gbps", "target": 35}, {"source": 33, "LinkLabel": "1-20Gbps", "target": 34}, {"source": 34, "LinkLabel": "10-20Gbps", "target": 35}, {"source": 34, "LinkLabel": "1-20Gbps", "target": 36}, {"source": 34, "LinkLabel": "1-20Gbps", "target": 37}, {"source": 34, "LinkLabel": "1-20Gbps", "target": 38}, {"source": 34, "LinkLabel": "1-20Gbps", "target": 39}, {"source": 34, "LinkLabel": "10-20Gbps", "target": 44}, {"source": 34, "LinkLabel": "1-20Gbps", "target": 48}, {"source": 34, "LinkLabel": "1-20Gbps", "target": 51}, {"source": 34, "LinkLabel": "1-20Gbps", "target": 62}, {"source": 34, "LinkLabel": "1-20Gbps", "target": 60}, {"source": 35, "LinkLabel": "1-20Gbps", "target": 47}, {"source": 35, "LinkLabel": "1-20Gbps", "target": 46}, {"source": 35, "LinkLabel": "1-20Gbps", "target": 55}, {"source": 35, "LinkLabel": "1-20Gbps", "target": 61}, {"source": 35, "LinkLabel": "1-20Gbps", "target": 63}, {"source": 42, "LinkLabel": "1-20Gbps", "target": 44}, {"source": 43, "LinkLabel": "1-20Gbps", "target": 44}, {"source": 44, "LinkLabel": "10-20Gbps", "target": 70}, {"source": 44, "LinkLabel": "1-20Gbps", "target": 45}, {"source": 49, "LinkLabel": "1-20Gbps", "target": 50}, {"source": 49, "LinkLabel": "10-20Gbps", "target": 59}, {"source": 52, "LinkLabel": "1-20Gbps", "target": 59}, {"source": 53, "LinkLabel": "1-20Gbps", "target": 59}, {"source": 54, "LinkLabel": "1-20Gbps", "target": 59}, {"source": 56, "LinkLabel": "1-20Gbps", "target": 59}, {"source": 66, "LinkLabel": "1-20Gbps", "target": 67}, {"source": 66, "LinkLabel": "10-20Gbps", "target": 70}, {"source": 67, "LinkLabel": "1-20Gbps", "target": 68}, {"source": 69, "LinkLabel": "1-20Gbps", "target": 70}, {"source": 70, "LinkLabel": "1-20Gbps", "target": 71}], "multigraph": true}